dimz/__init__.py
dimz/__main__.py
dimz/language_extensions.json
dimz/test.py
pydimz/__init__.py
pydimz/__main__.py
pydimz/language_extensions.json
pydimz/test.py
dimz-0.3.dist-info/LICENSE.txt
dimz-0.3.dist-info/METADATA
dimz-0.3.dist-info/WHEEL
dimz-0.3.dist-info/entry_points.txt
dimz-0.3.dist-info/top_level.txt
dimz-0.3.dist-info/RECORD
