Metadata-Version: 2.1
Name: dimz
Version: 0.3
Home-page: https://github.com/BrandonPacewic/dimz
Author: Brandon Pacewic
License: MIT
Classifier: Programming Language :: Python :: 3
Classifier: License :: OSI Approved :: MIT License
Requires-Python: >=3.10
License-File: LICENSE.txt
